csvld/__init__.py
csvld/main.py
csv_ld-0.0.2.dist-info/LICENSE
csv_ld-0.0.2.dist-info/METADATA
csv_ld-0.0.2.dist-info/WHEEL
csv_ld-0.0.2.dist-info/top_level.txt
csv_ld-0.0.2.dist-info/RECORD
