Metadata-Version: 2.1
Name: csv-ld
Version: 0.0.2
Summary: Tools for CSV-LD, a CSV-based Serialization for Linked Data 
Home-page: https://github.com/polyneme/nmdc-mongo-tools
Author: Donny Winston
Author-email: donny@polyneme.xyz
License: UNKNOWN
Platform: UNKNOWN
Classifier: Development Status :: 3 - Alpha
Classifier: Programming Language :: Python :: 3
Classifier: License :: OSI Approved :: Apache Software License
Requires-Python: >=3.8
Requires-Dist: fastapi[all]
Requires-Dist: python-dotenv
Requires-Dist: rdflib
Requires-Dist: requests
Requires-Dist: toolz
Provides-Extra: dev
Requires-Dist: black ; extra == 'dev'
Requires-Dist: invoke ; extra == 'dev'
Requires-Dist: pytest ; extra == 'dev'
Requires-Dist: setuptools-scm ; extra == 'dev'
Requires-Dist: twine ; extra == 'dev'
